cloudiscovery/__init__.py
cloudiscovery/commands/__init__.py
cloudiscovery/locales/__init__.py
cloudiscovery/locales/en_US/__init__.py
cloudiscovery/locales/en_US/LC_MESSAGES/__init__.py
cloudiscovery/locales/en_US/LC_MESSAGES/messages.mo
cloudiscovery/locales/pt_BR/__init__.py
cloudiscovery/locales/pt_BR/LC_MESSAGES/__init__.py
cloudiscovery/locales/pt_BR/LC_MESSAGES/messages.mo
cloudiscovery/provider/__init__.py
cloudiscovery/provider/aws/__init__.py
cloudiscovery/provider/aws/command.py
cloudiscovery/provider/aws/common_aws.py
cloudiscovery/provider/aws/all/__init__.py
cloudiscovery/provider/aws/all/command.py
cloudiscovery/provider/aws/all/data/__init__.py
cloudiscovery/provider/aws/all/data/omitted_resources.py
cloudiscovery/provider/aws/all/data/on_top_policies.py
cloudiscovery/provider/aws/all/data/required_params_override.py
cloudiscovery/provider/aws/all/exception/__init__.py
cloudiscovery/provider/aws/all/resource/__init__.py
cloudiscovery/provider/aws/all/resource/all.py
cloudiscovery/provider/aws/iot/__init__.py
cloudiscovery/provider/aws/iot/command.py
cloudiscovery/provider/aws/iot/diagram.py
cloudiscovery/provider/aws/iot/resource/__init__.py
cloudiscovery/provider/aws/iot/resource/certificate.py
cloudiscovery/provider/aws/iot/resource/policy.py
cloudiscovery/provider/aws/iot/resource/thing.py
cloudiscovery/provider/aws/limit/__init__.py
cloudiscovery/provider/aws/limit/command.py
cloudiscovery/provider/aws/limit/data/__init__.py
cloudiscovery/provider/aws/limit/data/allowed_resources.py
cloudiscovery/provider/aws/limit/resource/__init__.py
cloudiscovery/provider/aws/limit/resource/all.py
cloudiscovery/provider/aws/limit/resource/ses.py
cloudiscovery/provider/aws/policy/__init__.py
cloudiscovery/provider/aws/policy/command.py
cloudiscovery/provider/aws/policy/diagram.py
cloudiscovery/provider/aws/policy/resource/__init__.py
cloudiscovery/provider/aws/policy/resource/general.py
cloudiscovery/provider/aws/policy/resource/security.py
cloudiscovery-2.4.4.dist-info/LICENSE
cloudiscovery-2.4.4.dist-info/METADATA
cloudiscovery-2.4.4.dist-info/WHEEL
cloudiscovery-2.4.4.dist-info/top_level.txt
cloudiscovery-2.4.4.dist-info/RECORD
