Metadata-Version: 2.1
Name: cloudiscovery
Version: 2.4.4
Summary: The tool to help you discover resources in the cloud environment
Home-page: https://github.com/Cloud-Architects/cloudiscovery
Author: Cloud Architects
License: Apache License 2.0
Platform: UNKNOWN
Classifier: Development Status :: 5 - Production/Stable
Classifier: Environment :: Console
Classifier: Intended Audience :: System Administrators
Classifier: Natural Language :: English
Classifier: License :: OSI Approved :: Apache Software License
Classifier: Programming Language :: Python
Classifier: Programming Language :: Python :: 3.8
Requires-Python: >=3.8
Requires-Dist: boto3
Requires-Dist: ipaddress
Requires-Dist: diagrams (>=0.13)
Requires-Dist: jinja2 (<3.0)
Requires-Dist: cachetools
Requires-Dist: diskcache
Requires-Dist: pytz
